MANIFEST.in
README.md
setup.py
config/cmd.yaml
config/compute-fid.yaml
config/debug.yaml
config/mvtec-transforms.yaml
empty/__init__.py
empty/project.py
mnist/__init__.py
mnist/main.py
omnilearn/__init__.py
omnilearn/_info.py
omnilearn.egg-info/PKG-INFO
omnilearn.egg-info/SOURCES.txt
omnilearn.egg-info/dependency_links.txt
omnilearn.egg-info/not-zip-safe
omnilearn.egg-info/requires.txt
omnilearn.egg-info/top_level.txt
omnilearn/data/__init__.py
omnilearn/data/collate.py
omnilearn/data/collectors.py
omnilearn/data/loaders.py
omnilearn/data/manager.py
omnilearn/data/preprocess.py
omnilearn/data/register.py
omnilearn/data/samplers.py
omnilearn/data/samplers_old.py
omnilearn/eval/__init__.py
omnilearn/eval/evaluator.py
omnilearn/eval/fid/__init__.py
omnilearn/eval/fid/compute.py
omnilearn/eval/fid/fid.py
omnilearn/eval/fid/utils.py
omnilearn/legacy/__init__.py
omnilearn/legacy/pointnets.py
omnilearn/models/__init__.py
omnilearn/models/criterion.py
omnilearn/models/curriculum.py
omnilearn/models/features.py
omnilearn/models/layers.py
omnilearn/models/losses.py
omnilearn/models/nets.py
omnilearn/models/prior.py
omnilearn/models/regression.py
omnilearn/models/style.py
omnilearn/models/unsup/__init__.py
omnilearn/models/unsup/autoencoders.py
omnilearn/op/__init__.py
omnilearn/op/analysis.py
omnilearn/op/clock.py
omnilearn/op/download.py
omnilearn/op/evaluation.py
omnilearn/op/extensions.py
omnilearn/op/framework.py
omnilearn/op/loading.py
omnilearn/op/model.py
omnilearn/op/modes.py
omnilearn/op/pretrained.py
omnilearn/op/records.py
omnilearn/op/report.py
omnilearn/op/runs.py
omnilearn/op/training.py
omnilearn/op/configs/origin.yaml
omnilearn/op/datasets/__init__.py
omnilearn/op/datasets/disentangling.py
omnilearn/op/datasets/iam.py
omnilearn/op/datasets/mnist.py
omnilearn/op/datasets/mvtec.py
omnilearn/op/datasets/simple.py
omnilearn/op/datasets/transforms.py
omnilearn/op/datasets/translation.py
omnilearn/util/__init__.py
omnilearn/util/containers.py
omnilearn/util/data.py
omnilearn/util/distributions.py
omnilearn/util/farming.py
omnilearn/util/features.py
omnilearn/util/logging.py
omnilearn/util/logic.py
omnilearn/util/math.py
omnilearn/util/misc.py
