Metadata-Version: 1.0
Name: omnilearn
Version: 0.5.14
Summary: Powerful machine learning utilities for python
Home-page: https://github.com/felixludos/omni-learn
Author: Felix Leeb
Author-email: felixludos.info@gmail.com
License: MIT
Platform: UNKNOWN
